traffic_flow/__init__.py
traffic_flow/mtm.py
traffic_flow/mtm_ig_optimisation.py
traffic_flow/mtm_ig_undirected.py
traffic_flow/mtm_nx.py
traffic_flow/mtm_nx_undirected.py
traffic_flow/parameters.py
traffic_flow/sample_networks.py
traffic_flow/utils.py
traffic_flow/examples/network_1.xlsx
traffic_flow/examples/network_1_undirected.xlsx
traffic_flow/examples/network_2.xlsx
traffic_flow/examples/network_2_undirected.xlsx
traffic_flow-0.2.4.dist-info/LICENSE
traffic_flow-0.2.4.dist-info/METADATA
traffic_flow-0.2.4.dist-info/WHEEL
traffic_flow-0.2.4.dist-info/top_level.txt
traffic_flow-0.2.4.dist-info/RECORD
