Metadata-Version: 2.1
Name: traffic-flow
Version: 0.2.4
Summary: Macroscopic transport modelling; forecasting traffic flows on roads
Home-page: https://github.com/petervanya/traffic-flow
Author: Peter Vanya
Author-email: peter.vanya@gmail.com
License: GPLv3
Keywords: traffic flow modelling forecast optimisation transport
Classifier: Development Status :: 3 - Alpha
Classifier: Topic :: Scientific/Engineering
Classifier: Topic :: Software Development :: Libraries
Classifier: License :: OSI Approved :: GNU General Public License v3 (GPLv3)
Classifier: Operating System :: OS Independent
Classifier: Programming Language :: Python
Classifier: Programming Language :: Python :: 3
Requires-Python: >=3.9
License-File: LICENSE
Requires-Dist: numpy >=1.24
Requires-Dist: scipy >=1.10.1
Requires-Dist: pandas >=2.0.3
Requires-Dist: geopandas >=0.12.2
Requires-Dist: openpyxl >=3.1.2
Requires-Dist: networkx >=3.2.1
Requires-Dist: python-igraph >=0.11.3
